[
  {
    "title": "Safer Edmonton approach continues to reduce crime and disorder across the city",
    "url": "https://www.edmontonpolice.ca/News/MediaReleases/SaferEdmontonMay8",
    "date": null,
    "service_name": "Edmonton Police Service",
    "content": "Safer Edmonton approach continues to reduce crime and disorder across the city\nFor Immediate Release:\n08-May-2026 @ 8:01 AM\nMRU #:\n26R040\nThe Edmonton Police Service (EPS) is seeing continued success with its service-wide focus on reducing crime and disorder through visible enforcement, intelligence‑led deployments and data‑driven decision‑making in public spaces.\n“A safer Edmonton is not created through a short‑term initiative, it’s created through an ongoing policing standard in our service that guides how our officers are deployed, how enforcement is targeted, and how the service works with partners to improve safety across the city,” says Chief Warren Driechel. “These are the policing practices that will continue to guide the service’s day-to-day work.”\n“We are listening to Edmontonians’ concerns about disorder and crime and we’re addressing this through visible policing where it is needed most, especially as our city continues to grow and face unparalleled challenges with opioid use and its criminal supply.”\nTo help create a safer Edmonton, police are strategically deploying resources to Crime Treatment Zones. These are data-driven geographic areas within each police division and are used to determine where and when resources are needed. Based on community boundaries, crime data and mapping, the zones help identify emerging trends and guide targeted enforcement efforts.\nThrough these tools and the subsequent increase of police presence, the EPS has achieved measurable results in several communities including a reduced number of public calls for service related to crime and disorder in these targeted areas.\nIn central Edmonton, the newly deployed McCauley Beats and Chinatown Beats teams focused on the area around 96 Street and 106 Avenue. Over a two‑week period ending on March 20, 2026, officers conducted more than 175 public interactions that resulted in 17 arrests and 61 bylaw offence tickets issued.\nAdditionally, police have reported that crime and disorder in central Edmonton were lower in both reporting periods compared to last year.\nFrom March 12 to April 8, 2026, violent crime decreased by\n1.2 per cent. Non‑violent crime also declined, down 3.5 per cent overall from last year. Disorder saw the most significant reduction, decreasing by 13 per cent from last year.\nMoreover, breach and warrant execution occurrences increased by 29.5 per cent, reflecting proactive police activity where members encountered individuals with outstanding warrants or breaches of release conditions.\nIn northwest Edmonton, police targeted a chronic problem address in the Castledowns neighbourhood that had been generating almost 160 calls for police service, including assaults, weapons‑related complaints, mischief and disturbances. Through intelligence‑driven tools and proactive patrols, police were able to assist with getting the residence secured and boarded up, disrupting ongoing disorder and improving safety and comfort for nearby residents.\nTargeted enforcement has also continued in Edmonton’s south end. Working with Southgate Centre security and neighbouring businesses, police teams have made more than 50 arrests in the area since early February 2026. In early March, officers also carried out more than 50 proactive enforcement activities at Southgate LRT. Overall, disorder at Southgate LRT is down 20 per cent compared to April 28, 2025, violent crime is down 27 per cent year to date, and arrests are up 25 per cent over the same period.\n“Our service is aware that perceptions of disorder shape how safe people feel in their own neighbourhoods,” says Acting Superintendent Jared Hrycun with the EPS’ Southeast and Southwest Division. “Each community has its own challenges, meaning our approach to creating a safer Edmonton is uniquely tailored across the city through data-driven reporting. Whether it’s addressing a well-known problem property, tackling illegal drug use or increasing our presence at transit hubs, everyone has a right to a safer Edmonton and can expect\na continued coordinated, city\n‑\nwide effort focused on addressing disorder, reducing harm, and keeping our communities safe\n.”\nAs the weather warms up and we see more people in the heart of the city, over the next few weeks the EPS is focusing on the Crime Treatment Zone in and around Churchill Square. That means, especially during peak times, you can expect our officers to be highly visible as they address crime and disorder.\n-30-\nFor media inquiries please contact the EPS Media Relations Unit at\nmediarelations@edmontonpolice.ca\n.\n< Back to Media Releases Listing Page"
  },
  {
    "title": "Male charged after disturbance at LRT Station; weapon seized",
    "url": "https://www.edmontonpolice.ca/News/MediaReleases/LRTstationApr26",
    "date": null,
    "service_name": "Edmonton Police Service",
    "content": "Male charged after disturbance at LRT Station; weapon seized\nFor Immediate Release:\n07-May-2026 @ 9:40 AM\nMRU #:\n26R039\nThe Edmonton Police Service (EPS) has charged a 30-year-old\nmale with numerous firearm-related criminal offences following an incident at\nChurchill LRT Station in late April.\nOn Sunday, April 26, 2026, at around 6:53 p.m., police were called to assist EMS after it was reported that a male was interfering with the ability for first responders to help an individual at Churchill LRT Station. Police arrested the male and located a firearm in his backpack after a search incident to arrest. Thankfully, no injuries to the public were reported.\nThe accused male was in breach of a lifetime firearms ban as a result of a previous\nmanslaughter\ncharge.\nSkylar McGilvery, 30,\nis facing five charges including\npossess offensive weapon dangerous to public\n,\npossession of a firearm knowing possession unauthorized\n,\ncareless use of a firearm\n,\npossess prohibited firearm\nand\npossess prohibited firearm\n.\nSeized firearm\n“As our teams continue to address crime and disorder, especially in transit locations, we are committed to enforcing the law to keep our public spaces safe,” says Inspector Brent Dahlseide with the EPS’ Downtown Branch. “While we are remaining proactive on our patrols and efficient in our response times, we are encouraging the public to contact police immediately if they see something unsafe in our shared spaces. We can create a safer Edmonton by working together.”\n-30-\nFor media inquiries please contact the EPS Media Relations Unit at\nmediarelations@edmontonpolice.ca\n.\n< Back to Media Releases Listing Page"
  },
  {
    "title": "More complainants come forward leading to additional sexual assault charges",
    "url": "https://www.edmontonpolice.ca/News/MediaReleases/SAadditionalcomplainantsMay62026",
    "date": null,
    "service_name": "Edmonton Police Service",
    "content": "More complainants come forward leading to additional sexual assault charges\nFor Immediate Release:\n06-May-2026 @ 10:00 AM\nMRU #:\nSA26004 - 1\nFive additional women have come forward in an ongoing sexual assault investigation, bringing the total number of known complainants to nine. A 56-year-old man is now facing new charges, and police believe there may be additional complainants dating back to 2021.\nBackground\nIn April 2025, police received a report of a sexual assault involving a woman who met a man through a dating app. The woman had communicated with the suspect through online dating platforms such as Facebook Dating, Bumble and Tinder. The woman was later invited to the suspect’s home where investigators believe the suspect drugged and sexually assaulted her.\nWilliam McMullin\nwas arrested on March 17, 2026, and charged with multiple criminal charges. At the time of his arrest, police had confirmed four adult, female complainants.\nFollowing\na news release\nissued by the Edmonton Police Service (EPS) on March 25, 2026, five more women came forward. As a result, an additional 10 criminal charges have been laid\n– 22 in total – have been laid. These charges\ninclude\nsexual assault, administering a stupefying substance, assault with a weapon, voyeurism, assault, mischief under $5,000, intimidation, unlawful confinement and criminal harassment.\nInvestigators believe that\nMcMullin\nmay have offended in both Calgary and Edmonton.\n“We know that coming forward can take immense courage, and for many people, it may take time,” says Staff\nSergeant\nBrian McGuigan of the EPS Sexual Assault Section. “If you believe you were harmed, you are not alone. Our investigators are committed to approaching every report with compassion, dignity and care, and we encourage anyone with information, no matter how long ago the incident occurred, to reach out.”\nMcMullin\nremains in remand at this time. His next court date is scheduled for May 22, 2026.\nImage: William McMullin, 56\nAnyone who believes they may have been victimized by\nMcMullin\nis asked to contact the\nEdmonton Police Service at 780-423-4567\nor #377 from a mobile phone or the Calgary Police Service at 403-266-1234.\n-30-\nFor media inquiries please contact the EPS Media Relations Unit at\nmediarelations@edmontonpolice.ca\n.\n< Back to Media Releases Listing Page"
  },
  {
    "title": "Police arrest two teens after bus shelter assault",
    "url": "https://www.edmontonpolice.ca/News/MediaReleases/BusShelterArrestUpdateMay06",
    "date": null,
    "service_name": "Edmonton Police Service",
    "content": "Police arrest two teens after bus shelter assault\nFor Immediate Release:\n06-May-2026 @ 7:57 AM\nMRU #:\n26R035-1\nAfter receiving tips from the public, Edmonton Police Service (EPS) Northeast Branch officers arrested two teens responsible for an assault on an elderly female.\nOn April 19, 2026, around 9:00 a.m., Northeast Branch patrol officers responded to the report of an assault at a bus shelter in the area of McConachie Boulevard and 64 Street. A 66-year-old female had been approached by two young males, one had a fire extinguisher and discharged it, covering the senior and the bus shelter with powder before fleeing westbound. EMS attended and treated the senior who was released on scene.\nThrough tips from the public, investigators were able to identify two 13-year-old males who were subsequently arrested and charged. Further investigations revealed that either one or both males were involved in four different incidents: one male faces charges including\nassault with a weapon\n,\nhousebreaking with intent\n,\nmischief under $5,000\nand theft under $5,000\n, while the other male faces charges of\ntheft under $5000\nand\nassault with a weapon\n.\n“I would like to take this opportunity to thank the public for their assistance in this matter,” says Const. Arthur Rekshta of the EPS Northeast Division. “The tips we received allowed us to identify suspects and also link them to other events that were still under investigation.”\nAnyone with any information about this or any other crime is asked to contact the EPS at 780-423-4567\nor #377 from a mobile phone. Anonymous information can also be submitted to Crime Stoppers at 1-800-222-8477 or online at\nwww.p3tips.com/250\n.\n-30-\nFor media inquiries please contact the EPS Media Relations Unit at\nmediarelations@edmontonpolice.ca\n.\n< Back to Media Releases Listing Page"
  },
  {
    "title": "Police seeking witnesses in collision turned fatal",
    "url": "https://www.edmontonpolice.ca/News/MediaReleases/fatalMay5",
    "date": null,
    "service_name": "Edmonton Police Service",
    "content": "Police seeking witnesses in collision turned fatal\nFor Immediate Release:\n05-May-2026 @ 9:53 AM\nMRU #:\nTR26008\nThe Edmonton Police Service (EPS) is\nseeking witnesses to an April 30 collision that later turned fatal.\nAt approximately 1:30 p.m. on Thurs., April 30, 2026, a 2026 Toyota Camry operated by an 82-year-old male was exiting from westbound Whitemud Drive onto northbound 170 Street. As the Camry entered the intersection of the Whitemud off-ramp and the northbound lanes of 170 Street, it was struck on the driver’s side by a northbound 2010 Mazda 3 operated by a 29-year-old male. No injuries were reported, and the parties attended a Collision Reporting Centre on their own.\nFollowing the collision, the condition of a 78-year-old female passenger in the Camry declined significantly at home, and on May 2, she was transported to hospital by ambulance. She died in hospital on May 3, and police were notified the following day.\nThe EPS Major Collision Investigations Section (MCIS) has taken over the investigation, and is seeking witnesses or dashcam footage from anyone traveling in the area at the time.\nWitnesses or motorists with dashcam footage related to this collision are asked to contact EPS at 780-423-4567 or #377 from a mobile phone.\n-30-\nFor media inquiries please contact the EPS Media Relations Unit at\nmediarelations@edmontonpolice.ca\n.\n< Back to Media Releases Listing Page"
  },
  {
    "title": "Police seek assistance identifying suspect in shooting",
    "url": "https://www.edmontonpolice.ca/News/MediaReleases/ShootingsuspectMay1",
    "date": null,
    "service_name": "Edmonton Police Service",
    "content": "Police seek assistance identifying suspect in shooting\nFor Immediate Release:\n01-May-2026 @ 2:30 PM\nMRU #:\n26R041\nThe Edmonton Police Service (EPS) is seeking the public's assistance identifying a suspect, following a shooting in the Clareview neighbourhood earlier this month.\nOn April 5, 2026, Northeast Branch patrol officers were called about shots fired near a schoolyard in the area of 133 Avenue and Clareview Rd at approximately 4 a.m. It was reported to police that one shot struck a nearby home, entering a bedroom and narrowly missing a young child who was sleeping at the time. Police do not believe the residence was targeted.\nMap of shooting location\nInvestigators believe one person is responsible for firing the shots, following a brief meeting with someone in and unknown vehicle. Images of the suspect and the vehicle are included below.\nImage of suspect\nImage of unknown vehicle\n“A brazen shooting in a residential neighbourhood is concerning, in particular when a child was directly in harm’s way,” says Acting Inspector Eric Stewart with the Investigations Response Teams IRT. “We’re thankful to not be reporting on more dire circumstances today and are appealing to residents for any information they may recall about a shooting that night.”\nEPS Patrol and IRT continue to investigate and are asking anyone with information regarding the shooting, the suspect, or the vehicle to contact the EPS at 780-423-4567\nor #377 from a mobile phone. Anonymous information can be submitted to Crime Stoppers at 1-800-222-8477 or online at\nwww.p3tips.com/250\n.\n-30-\nFor media inquiries please contact the EPS Media Relations Unit at\nmediarelations@edmontonpolice.ca\n.\n< Back to Media Releases Listing Page"
  },
  {
    "title": "Police seek witnesses and dashcam footage of collision in southwest",
    "url": "https://www.edmontonpolice.ca/News/MediaReleases/SeekingWitnesses23AvenueApril28026",
    "date": null,
    "service_name": "Edmonton Police Service",
    "content": "Police seek witnesses and dashcam footage of collision in southwest\nFor Immediate Release:\n28-Apr-2026 @ 1:32 PM\nMRU #:\nTR26007\nThe Edmonton Police Service (EPS) is asking anyone who may have witnessed a collision in the city's southwest to come forward.\nAround 8:30 a.m. on Mon., April 27, 2026, a two-vehicle collision occurred at the intersection of Terwillegar Drive and 23 Avenue. Police believe a northbound Mazda CX-5 and an eastbound Mercedes Benz collided in the southwest corner of the intersection.\nA 38-year-old female was treated by EMS and transported to hospital with non-life-threatening injuries. No other injuries were reported at the time.\nThe EPS Major Collision Investigations Section (MCIS) has since taken over the investigation.\nAnyone who may have witnessed the collision or have dash camera footage is asked to contact the EPS at 780-423-4567 or #377 from a mobile phone.\n-30-\nFor media inquiries please contact the EPS Media Relations Unit at\nmediarelations@edmontonpolice.ca\n.\n< Back to Media Releases Listing Page"
  },
  {
    "title": "Police seeking tips, video related to 2025 shooting",
    "url": "https://www.edmontonpolice.ca/News/MediaReleases/2025Marchshooting",
    "date": null,
    "service_name": "Edmonton Police Service",
    "content": "Police seeking tips, video related to 2025 shooting\nFor Immediate Release:\n28-Apr-2026 @ 11:10 AM\nMRU #:\n26R038\nThe Edmonton Police Service (EPS) is seeking\ntips and video footage following a shooting that took place in northeast\nEdmonton in March 2025.\nOn March 30, 2025, police were called regarding an adult male who attended a medical facility with a gunshot wound. It was reported to police that he was sleeping in his home in the area of 34 Street and Abbottsfield Road when he awoke around 5:40 a.m. with an unknown injury. The male sustained a non-life-threatening injury.\n“This resident has no criminal involvement, and his residence is not known to police,” says Det. Andrew Furman with the EPS Investigations Response Team. “This incident emphasizes the inherent danger to innocent bystanders when shootings take place, and we are grateful that his injuries were not more severe or fatal.”\nTo date, police have exhausted all efforts to gather more information in relation to the shooting and are hopeful someone who was in the area at the time or was driving nearby may have information or video footage that will help further the investigation. A map is included below for reference.\nMap of 2025 shooting location\nAnyone with home security/dash cam video that was active on March 30, 2025, between 5 a.m. and 6 a.m. is asked\nto contact the EPS at 780-423-4567\nor #377 from a mobile phone. Anonymous information can also be submitted to Crime Stoppers at 1-800-222-8477 or online at\nwww.p3tips.com/250\n.\n-30-\nFor media inquiries please contact the EPS Media Relations Unit at\nmediarelations@edmontonpolice.ca\n.\n< Back to Media Releases Listing Page"
  },
  {
    "title": "Charge laid in 2023 homicide",
    "url": "https://www.edmontonpolice.ca/News/MediaReleases/HomicideChargesApril27",
    "date": null,
    "service_name": "Edmonton Police Service",
    "content": "Charge laid in 2023 homicide\nFor Immediate Release:\n27-Apr-2026 @ 3:01 PM\nMRU #:\nH23R042-1\nThe Edmonton Police Service (EPS) has charged a 50-year-old man with second degree murder in relation to a 2023 homicide in Southwest Edmonton.\nOn Wednesday, October 11, 2023, at approximately 10:00 a.m., police responded to the report of a weapons complaint in an apartment building in the area of 106 Street and 80 Avenue. Upon arrival a male was located with serious, life-threatening injuries. EMS responded but the male succumbed to his injuries and was pronounced deceased on scene.\nLater that month,\nthe Edmonton Medical Examiner confirmed\nJordan McDonald, 33,\ndied as a result of a homicide. The cause of death was a gunshot wound.\nOn Saturday, April 25, 2026,\nSean Broadley, 50,\nwas arrested and charged with\nsecond degree murder\n. The victim and accused were not known to one another.\nAnyone with information about this homicide is asked to contact the EPS at 780-423-4567 or #377 from a mobile phone. Anonymous information can also be submitted to Crime Stoppers at 1-800-222-8477 or online at\nwww.p3tips.com/250\n.\n-30-\nFor media inquiries please contact the EPS Media Relations Unit at\nmediarelations@edmontonpolice.ca\n.\n< Back to Media Releases Listing Page"
  },
  {
    "title": "Police investigating fatal collision in southwest Edmonton",
    "url": "https://www.edmontonpolice.ca/News/MediaReleases/fatalcoll41SW",
    "date": null,
    "service_name": "Edmonton Police Service",
    "content": "Police investigating fatal collision in southwest Edmonton\nFor Immediate Release:\n26-Apr-2026 @ 5:00 PM\nMRU #:\nTR26006\nThe Edmonton Police Service\n(EPS) is investigating a fatal single-vehicle collision that took place early\nthis morning on 41 Avenue SW.\nAt approximately 2:40 a.m., on Sunday, April 26, 2026, a 1991 BMW 735i was travelling westbound on 41 Avenue SW when it lost control and left the roadway on the north side of 41 Avenue SW just west of Allard Rd SW. The vehicle then struck two trees and a light standard before coming to a stop.\nThe 25-year-old male driver of the BMW was declared deceased on scene. There were no other occupants in the vehicle.\nEPS Major Collision Investigations Section (MCIS) continues to investigate. Road conditions are not believed to have contributed to this collision; however, speed is considered a factor.\n-30-\nFor media inquiries please contact the EPS Media Relations Unit at\nmediarelations@edmontonpolice.ca\n.\n< Back to Media Releases Listing Page"
  },
  {
    "title": "Police seek assistance locating missing teen",
    "url": "https://www.edmontonpolice.ca/News/MediaReleases/MissingPersonApril24",
    "date": null,
    "service_name": "Edmonton Police Service",
    "content": "Police seek assistance locating missing teen\nFor Immediate Release:\n24-Apr-2026 @ 5:15 PM\nMRU #:\nMP26R011\nThe Edmonton Police Service (EPS) is seeking the public's assistance in locating a missing teen.\nPrayag Dalbhatwala\nwas last seen on April 23, 2026, around 4 p.m. at a residence in the area of 99 St. and 90 Ave. He was supposed to go to Calgary but cancelled his plans at the last minute and has not been seen or heard from since.\nPrayag\nis 5’9” with a medium build, he has dark hair and wears glasses. He was last seen wearing green camo joggers and a black Bench hoodie.\nMissing teen: Prayag Dalbhatwala, 19\nMissing teen: Prayag Dalbhatwala, 19\nPrayag\nis known to frequent the University of Alberta. His disappearance is out of character and his family and police are concerned about his well-being.\nAnyone with information about\nPrayag Dalbhatwala’s\nwhereabouts is asked to contact the EPS at 780-423-4567\nor #377 from a mobile phone.\n-30-\nFor media inquiries please contact the EPS Media Relations Unit at\nmediarelations@edmontonpolice.ca\n.\n< Back to Media Releases Listing Page"
  },
  {
    "title": "Public precaution issued following harassment incidents at post-secondary campus",
    "url": "https://www.edmontonpolice.ca/News/MediaReleases/dutytowarnAhmed",
    "date": null,
    "service_name": "Edmonton Police Service",
    "content": "Public precaution issued following harassment incidents at post-secondary campus\nFor Immediate Release:\n24-Apr-2026 @ 2:15 PM\nMRU #:\nSA26R007\nThe Edmonton Police Service\n(EPS) is issuing a notice to the public regarding a 33-year-old male who\nwas recently involved in harassment-related incidents at the University of\nAlberta (U of A) campus.\nTwice in March 2026,\nMuhammad Ahmed\nattended the U of A campus and demonstrated a pattern of concerning behaviour in public spaces. This includes engaging in unwanted interactions with females that have escalated to harassment and, at times, threatening or aggressive conduct.\nAhmed\nis known to police and also has a history of similar interactions in other public spaces in Edmonton and other Canadian cities.\nAhmed\nwas arrested and charged with u\nnlawful interference with enjoyment of property (mischief)\nand\ntwo counts of failing to comply with conditions\nand is now subject to a court order with conditions, including that he stay away from the U of A campus.\nMuhammad Ahmed, 33\n“Police would like to remind all members of the public to stay aware of their surroundings,”\nsays Acting Staff Sergeant Brian McGuigan with the EPS Sexual Assault Section. “Additionally, if you suddenly find someone is engaging you in a threatening, aggressive or hostile manner, tell them clearly to leave you alone, and proceed to the closest, well-lit populated area before calling for help.”\nAnyone who notices\nAhmed\non the U of A campus\nor has a hostile interaction with him in a public space elsewhere is encouraged to contact the EPS at 780-423-4567 or #377 from a mobile phone.\n-30-\nFor media inquiries please contact the EPS Media Relations Unit at\nmediarelations@edmontonpolice.ca\n.\n< Back to Media Releases Listing Page"
  },
  {
    "title": "Police seek assistance to identify armed robbery victim",
    "url": "https://www.edmontonpolice.ca/News/MediaReleases/asstidvic",
    "date": null,
    "service_name": "Edmonton Police Service",
    "content": "Police seek assistance to identify armed robbery victim\nFor Immediate Release:\n24-Apr-2026 @ 10:02 AM\nMRU #:\n26R037\nThe Edmonton Police Service (EPS) is seeking the public’s help to\nidentify a man who was robbed by a suspect with a hatchet in March.\nPolice are investigating an armed robbery that occurred on Wednesday, March 25, 2026, at approximately 10:15 a.m. at MacEwan LRT station. Police have identified the suspect, who was captured on Edmonton Transit\nsurveillance using a hatchet to cut the victim’s backpack strap, forcibly removing it, and then leaving via a departing train. The victim in the robbery has yet to come forward, and investigators would like to speak with them in order to ensure they were not injured\n.\nPolice would like to speak with the victim, pictured in this image captured from transit security footage.\nPolice are asking anyone with information about the victim’s identity to contact the EPS at 780-423-4567\nor #377 from a mobile phone. Anonymous information can also be submitted to Crime Stoppers at 1-800-222-8477 or online at\nwww.p3tips.com/250\n.\n-30-\nFor media inquiries please contact the EPS Media Relations Unit at\nmediarelations@edmontonpolice.ca\n.\n< Back to Media Releases Listing Page"
  },
  {
    "title": "Edmonton Police investigation leads to charges against daycare worker",
    "url": "https://www.edmontonpolice.ca/News/MediaReleases/DaycareFileApril2026",
    "date": null,
    "service_name": "Edmonton Police Service",
    "content": "Edmonton Police investigation leads to charges against daycare worker\nFor Immediate Release:\n22-Apr-2026 @ 4:00 PM\nMRU #:\nSA26R006\nThe Edmonton Police Service (EPS) has charged a 21-year-old daycare employee following a sexual assault investigation and believe there may be more complainants.\nOn April 8, 2026, a parent called police to report an incident involving their child at a west Edmonton daycare. Through investigative measures, officers identified a teaching assistant as the suspect, who was then suspended by his employer. His childcare certification has also been suspended.\nOn April 21, 2026,\nKulraj Singh, 21,\nwas arrested and charged with\nsexual assault and sexual interference.\nImage of the accused: Kulraj Singh, 21\nSingh\nwas released on bail with conditions including having no contact with the complainant, not attending public swimming pools, schools or school yards, daycares, playgrounds, libraries or youth shelters unless accompanied by a sober adult who is aware of the charges, and not seeking or maintaining any position of trust or authority over a person under the age of 16.\nSingh\nalso worked at a second daycare in central Edmonton.\nPolice believe there may be additional complainants and are asking anyone with information to come forward. You can contact the\nEPS at 780-423-4567\nor #377 from a mobile phone. The EPS can also provide appropriate supports. Anonymous information may also be submitted to Crime Stoppers at 1-800-222-8477 or online\nat\nwww.p3tips.com/250\n.\n-30-\nFor media inquiries please contact the EPS Media Relations Unit at\nmediarelations@edmontonpolice.ca\n.\n< Back to Media Releases Listing Page"
  },
  {
    "title": "EPS Emergency Communications and Operations Branch welcomes 103 new graduates",
    "url": "https://www.edmontonpolice.ca/News/MediaReleases/2026_ECOMB_Graduation",
    "date": null,
    "service_name": "Edmonton Police Service",
    "content": "EPS Emergency Communications and Operations Branch welcomes 103 new graduates\nFor Immediate Release:\n22-Apr-2026 @ 3:00 PM\nMRU #:\n26R036\nThe Edmonton Police Service (EPS) proudly welcomed 103 graduates to its Emergency Communications and Operations Management Branch (ECOMB) during a formal graduation ceremony held Wednesday, April 22, 2026, at City Hall.\nThe graduating class included 35 new civilian Emergency Communications Officers (ECOs) along with 68 additional graduates from Evaluation, Dispatch, and other operational support roles.\nECOs perform critical functions: 911 operator, police evaluator, and dispatcher. All candidates begin as 911 operators which includes four days of classroom training and four days of on the floor training with an experienced coach.\nECOs then progress to the police evaluator role, which includes five weeks of classroom instruction and approximately seven weeks of supervised, on-the-job training while working on regular shift rotations. After one to two years as an evaluator, members may advance to dispatcher training. This final stage includes 10 weeks of course material completed during regular shifts, followed by a 16 week program that combines classroom learning with hands-on operational training.\nECOMB serves as Edmonton’s primary Public Safety Answering Point (PSAP), handling approximately 3,000 calls every day from the public. These calls, which encompass both 9-1-1 emergencies needing police, fire, or ambulance and non-emergency inquiries, are answered, evaluated, and dispatched accordingly. ECOs serve as the vital connection between the community and the public safety services they depend on.\nBecoming an ECO requires a highly competitive application and selection process, with fewer than 6 per cent of first-time applicants selected for training. The training prepares members to perform effectively in high-pressure situations where accuracy, empathy, and utilizing their quick decision-making skills are critical. Graduates bring diverse backgrounds to the Branch, including customer service, law, science, and military experience.\nDuring a standard 12-hour shift, an ECO may speak with upwards of 80 callers. In 2025 alone, ECOMB handled more than one million emergency and non-emergency calls, including over 600,000 emergencies with 96.3% of calls answered within 15 seconds. Behind each of those calls are more than 200 dedicated ECOs working around the clock to answer, evaluate, and dispatch help – 24 hours a day, 7 days a week.\nAlthough their work happens behind the scenes, the impact they have on public safety is immeasurable. This is all the more reason to celebrate their achievements and recognize the critical role they play in keeping residents safe. As the first of the first responders, ECOs ensure the fast and accurate transmission of information related to fire, medical and law enforcement emergencies.\nThe professionalism of ECOMB was demonstrated during a critical incident that occurred in late 2025 when an ECO stepped in to provide American Sign Language (ASL) translation for a hearing-impaired individual. Her compassion and quick action enabled effective communication and were key to the successful resolution -one of many examples of the vital work ECOs do every day.\n“We are proud to welcome our newest Emergency Communications Officers to the ECOMB team, says ECOMB Director, Kay Anderson. “As the First of the First Responders, your dedication and service make a meaningful difference in our community every day, you are the calm voice in crisis and a vital link in every emergency response.”\nEPS congratulates all graduates on their achievement and thanks them for their commitment to public safety.\nFor more information about a career as an ECO, please visit\n911maketherightcall.ca\nor the ECOMB page at\nedmontonpolice.ca/ECOMB\n-30-\nFor media inquiries please contact the EPS Media Relations Unit at\nmediarelations@edmontonpolice.ca\n.\n< Back to Media Releases Listing Page"
  },
  {
    "title": "Police seeking public’s assistance identifying assault suspects",
    "url": "https://www.edmontonpolice.ca/News/MediaReleases/NEassaultApr21",
    "date": null,
    "service_name": "Edmonton Police Service",
    "content": "Police seeking public’s assistance identifying assault suspects\nFor Immediate Release:\n21-Apr-2026 @ 3:05 PM\nMRU #:\n26R035\nEdmonton Police Service (EPS) Northeast Branch officers are seeking the public’s assistance in identifying two suspects responsible for an assault on an elderly female Sunday morning.\nOn April 19, 2026, around 9:00 a.m., Northeast Branch patrol officers responded to the report of an assault at a bus shelter in the area of McConachie Boulevard and 64 Street. A 66-year-old female had been approached by two young males, one had a fire extinguisher and discharged it, covering the senior and the bus shelter with powder before fleeing westbound. EMS attended and treated the senior who was released on scene.\nThe suspects are described as:\nSuspect #1:\nBlack male, wearing a black jacket with a hoodie. He discharged the fire extinguisher.\nSuspect #2:\nLight skinned male, wearing a white hoodie.\n“This was a completely unprovoked and random attack on a senior citizen,” says Const. Arthur Rekshta of the EPS Northeast Division. “We’re hopeful someone with information about this incident will come forward so we can hold these people accountable for this unacceptable action.”\nAnyone with information about the suspects or this incident is asked to contact the\nEPS at 780-423-4567\nor #377 from a mobile phone. Anonymous information can also be submitted to Crime Stoppers at 1-800-222-8477 or online at\nwww.p3tips.com/250\n.\n-30-\nFor media inquiries please contact the EPS Media Relations Unit at\nmediarelations@edmontonpolice.ca\n.\n< Back to Media Releases Listing Page"
  },
  {
    "title": "Tattoo artist charged with sexual assault",
    "url": "https://www.edmontonpolice.ca/News/MediaReleases/tattooartistApr20",
    "date": null,
    "service_name": "Edmonton Police Service",
    "content": "Tattoo artist charged with sexual assault\nFor Immediate Release:\n20-Apr-2026 @ 1:07 PM\nMRU #:\nSA26R005\nThe Edmonton Police Service (EPS) has charged a male\ntattoo artist with sexual assault.\nPolice began an investigation following reports of sexual assaults involving a tattoo artist. Most of the incidents are reported to have occurred in 2025, with at least one dating back to 2021. On multiple occasions, while tattooing female clients, the accused touched them in a sexual manner.\nOn Apr. 18, 2026,\nIskotew Gladu, 40,\nwas arrested and charged with five counts of\nsexual assault.\nGladu\nwas released with conditions including:\nNot to have contact with the complainants\nNot to be in possession of a weapon of any kind\nIf he continues to be employed as a tattoo artist, he is not permitted to provide services to any client alone\nGladu\nis known to have provided services at two tattoo businesses in north and central Edmonton, including near 118 Avenue and St. Albert Trail and Kingsway Mall.\nIskotew Gladu, 40\nInvestigators believe there may be additional complainants and are asking anyone who may have had a similar experience with Gladu to come forward. Support is available for anyone affected by sexual violence though local sexual assault support services or through the EPS.\nThe EPS is asking anyone with information to contact the EPS at 780-423-4567\nor #377 from a mobile phone. Anonymous information may also be submitted to Crime Stoppers at 1-800-222-8477 or online at\nwww.p3tips.com/250\n.\n-30-\nFor media inquiries please contact the EPS Media Relations Unit at\nmediarelations@edmontonpolice.ca\n.\n< Back to Media Releases Listing Page"
  },
  {
    "title": "Police seek assistance locating missing woman",
    "url": "https://www.edmontonpolice.ca/News/MediaReleases/MissingWomanApril15",
    "date": null,
    "service_name": "Edmonton Police Service",
    "content": "Police seek assistance locating missing woman\nFor Immediate Release:\n15-Apr-2026 @ 1:02 PM\nMRU #:\nMP26R010\nThe Edmonton Police Service (EPS) is seeking the public’s assistance in locating a missing 37-year-old woman.\nShe is described as 5’1”, has a slim build and blue eyes. Smith has changed her hair frequently over the years and was last seen with long blonde and black hair. She has a tattoo on the left side of her head and has a bracelet-style tattoo on her wrist. Smith was last seen wearing blue plaid pants and a white jacket with a dark sweater underneath, as pictured below.\nCarole Smith, 37, with coloured hair\nLast seen: Carole Smith, 37\nImage of tattoo on head: Carole Smith\nSmith has been known to frequent 118 Avenue and Kingsway and is known to use support services in central Edmonton. Smith’s disappearance is out of character, and her family and police are concerned about her well-being.\nAnyone with information about Carole Smith’s whereabouts is asked to contact the EPS at 780-423-4567\nor #377 from a mobile phone.\nAnonymous information can also be submitted to Crime Stoppers at 1-800-222-8477 or online at\nwww.p3tips.com/250\n.\n-30-\nFor media inquiries please contact the EPS Media Relations Unit at\nmediarelations@edmontonpolice.ca\n.\n< Back to Media Releases Listing Page"
  },
  {
    "title": "Police lay charges in stabbing at Jasper Place School",
    "url": "https://www.edmontonpolice.ca/News/MediaReleases/jasperplacestabbingApril",
    "date": null,
    "service_name": "Edmonton Police Service",
    "content": "Police lay charges in stabbing at Jasper Place School\nFor Immediate Release:\n13-Apr-2026 @ 4:00 PM\nMRU #:\n26R034\nThe Edmonton Police Service (EPS) has charged a male\nyouth in relation to a stabbing at a west end school last Friday.\nAt approximately 11:58 a.m. on Friday, April 10, 2026, West Branch Patrol officers responded to the report of a stabbing at Jasper Place School in the area of 89 Avenue and 163 Street. It was reported to police that a 16-year-old male suspect confronted another 16-year-old male regarding a verbal argument that had taken place earlier in the day. The complainant reportedly attempted to walk away from the conversation when he was stabbed. Several youths attempted to restrain the suspect; however, he was able to break free and leave the school.\nAn EPS School Resource Officer (SRO) immediately arrived on scene, and assisted school staff with life-saving measures. EMS then treated and transported the male youth to hospital with life-threatening injuries. He has since been released from hospital and is recovering at home.\nThe school was immediately placed on lockdown and patrol officers quickly located the suspect nearby and took him into custody without incident. The 16-year-old male suspect has since been charged with offences of\naggravated assault\n,\nassault with a weapon\n,\npossession of a weapon,\nand\ncriminal harassment.\n“We are grateful for the immediate life-saving actions of school staff and our SRO, as well as the rapid response of our frontline patrol members and school partners,” says Staff Sergeant Derek Onysko with the EPS Youth Integrated Services Section.\n“Thanks to their fast and unified actions, a dangerous situation was handled quickly and with care and school and community safety were swiftly restored.”\n-30-\nFor media inquiries please contact the EPS Media Relations Unit at\nmediarelations@edmontonpolice.ca\n.\n< Back to Media Releases Listing Page"
  },
  {
    "title": "Police seek assistance locating missing woman",
    "url": "https://www.edmontonpolice.ca/News/MediaReleases/MissingWomanApril92026",
    "date": null,
    "service_name": "Edmonton Police Service",
    "content": "Police seek assistance locating missing woman\nFor Immediate Release:\n09-Apr-2026 @ 9:07 AM\nMRU #:\nMP26R009\nThe Edmonton Police Service (EPS) is seeking the public's assistance in locating a missing 42-year-old woman.\nJunell Calliou\nwas reported missing on February 28, 2026. To date, efforts to locate her have been unsuccessful.\nJunell was last seen at West Edmonton Mall and near Stony Plain Road and 156 Street during the month of February.\nShe is described as 5’4” and weighing approximately 115 lbs. She has the word “Jada” tattooed on the left side of her neck and a purple birthmark on her left wrist.\nImage: Junell Calliou, 42\nImage: Junell Calliou, 42\nJunell has been known to use different names and frequent West Edmonton Mall, Stony Plain Road and central Edmonton. Junell has a medical condition, and her family and police are concerned for her wellbeing.\nAnyone with information about\nthe\nwhereabouts of Junell Calliou is asked to contact the EPS at 780-423-4567\nor #377 from a mobile phone.\n-30-\nFor media inquiries please contact the EPS Media Relations Unit at\nmediarelations@edmontonpolice.ca\n.\n< Back to Media Releases Listing Page"
  },
  {
    "title": "Autopsy complete in west Edmonton death",
    "url": "https://www.edmontonpolice.ca/News/MediaReleases/AutopsyApril8",
    "date": null,
    "service_name": "Edmonton Police Service",
    "content": "Autopsy complete in west Edmonton death\nFor Immediate Release:\n08-Apr-2026 @ 8:36 AM\nMRU #:\nH26R005-1\nThe man found deceased in west Edmonton was the victim of a homicide.\nOn Apr. 3, 2026, at approximately 9:36 p.m., police responded to reports of an injured male at a residence in the area of 82 Avenue NW and 175 Street NW. Upon arrival, a 52-year-old male was taken to hospital by EMS where he was pronounced deceased a short time later. A male youth was arrested on scene without incident.\nAn autopsy completed on Tuesday, Apr. 7, 2026, confirmed the victim, a 52-year-old male, died as a result of a homicide.\nPolice charged a male youth with\nsecond degree murder\n. The youth accused is known to the victim and police are withholding their identities and the cause of death for investigative purposes.\nAnyone with information about this homicide is asked to contact the EPS at 780-423-4567 or #377 from a mobile phone. Anonymous information can also be submitted to Crime Stoppers at 1-800-222-8477 or online at\nwww.p3tips.com/250\n.\n-30-\nFor media inquiries please contact the EPS Media Relations Unit at\nmediarelations@edmontonpolice.ca\n.\n< Back to Media Releases Listing Page"
  },
  {
    "title": "Police seek additional complainants in fraud investigation",
    "url": "https://www.edmontonpolice.ca/News/MediaReleases/odometerfraudMarch26",
    "date": null,
    "service_name": "Edmonton Police Service",
    "content": "Police seek additional complainants in fraud investigation\nFor Immediate Release:\n07-Apr-2026 @ 11:30 AM\nMRU #:\n26R026\nThe Edmonton Police Service is seeking additional\ncomplainants after a 39 -year-old man was charged with fraud for altering the\nodometer on vehicles to sell them for higher prices.\nOn March 13, 2026, police received a report that a vehicle that had been purchased via Facebook Marketplace appeared to have an altered odometer, resulting in the purchaser paying a price much higher than the vehicle’s actual value. Following an investigation, police arrested and charged\nHarmandeep Singh Bindra, 39,\nwith\nfraud\nand\nuttering a forged document.\nInvestigators believe that\nBindra\nhas purchased several high-mileage vehicles via Facebook Marketplace since March 2025, changed the odometer on the vehicles by hundreds of thousands of kilometers and then sold the vehicles at a significantly higher price using a false Facebook account.\nBindra\nhas also reportedly provided false CARFAX reports to prospective buyers as proof that the vehicles have a lower odometer reading than they do.\nBindra\nis known to buy and sell primarily Nissan Altimas, Honda Accords and Honda CRVs and may use aliases such as Hary Smith, Harry Singh, Harmandeep Singh and Gurdev.\nTo date, police have identified at least two complainants but believe there may be many more and are releasing Bindra’s photo to encourage them to come forward.\nHarmandeep Singh Bindra, 39\nAnyone who believes they may have been victimized by\nBindra\nis encouraged to call the EPS at 780-423-4567\nor #377 from a mobile phone. Anonymous information can also be submitted to Crime Stoppers at 1-800-222-8477 or online at\nwww.p3tips.com/250\n.\nIf you plan to purchase a used vehicle via a private seller, investigators recommend reviewing the following tips from the\nEPS\nand\nService Alberta:\nAsk for proof of ownership and identification from the seller\n- Compare photo identification to the name on the vehicle’s registration document and make sure they are the same. Record the seller’s driver’s license number and contact information on the bill of sale.\nContact a\nregistry agent\nor\nAMA\nto get a vehicle information report\n- this describes the vehicle’s registration history in Alberta.\nConsider online services such as CARFAX\n– Purchase this report on your own to ensure it has not been falsified. Also look for any noted colour changes and/or odometer discrepancies. Pay particular attention to a vehicle’s registration history. If the vehicle goes back and forth several times between provinces and/or states, it may be a clone.\nGet a safety inspection of the vehicle from a\nvehicle inspection facility\n.\nKeep detailed records of the transaction -\nRetain original copies of bills of sale, registrations, service records etc.\n“When you are making a significant purchase like a vehicle, it is always a good idea to do your research first,” says Const. Amelia Towns with EPS Southwest Patrol Branch. “A CARFAX report will tell you the service history and any collisions the vehicle has been in. The small investment in this report may save you from the significant inconvenience of being scammed.”\n-30-\nFor media inquiries please contact the EPS Media Relations Unit at\nmediarelations@edmontonpolice.ca\n.\n< Back to Media Releases Listing Page"
  },
  {
    "title": "Police investigating suspicious death",
    "url": "https://www.edmontonpolice.ca/News/MediaReleases/SusDeathApril4",
    "date": null,
    "service_name": "Edmonton Police Service",
    "content": "Police investigating suspicious death\nFor Immediate Release:\n04-Apr-2026 @ 10:35 AM\nMRU #:\nH26R005\nThe Edmonton Police Service (EPS) is investigating a death that took place yesterday in west Edmonton.\nOn Apr. 3, 2026, at approximately 9:36 p.m., police responded to reports of an injured male at a residence in the area of 82 Avenue NW and 175 Street NW. Upon arrival, a 52-year-old male was taken to hospital by EMS where he was pronounced deceased a short time later. A male youth was arrested on scene without incident.\nPolice have deemed this death to be suspicious, and the investigation has since been turned over to the EPS Homicide Section. At this time, police are not seeking any additional suspects.\nAn autopsy has been scheduled for Tuesday, Apr. 7, 2026.\nAnyone with information about this suspicious death is asked to contact the EPS at 780-423-4567 or #377 from a mobile phone. Anonymous information can also be submitted to Crime Stoppers at 1-800-222-8477 or online at\nwww.p3tips.com/250\n.\n-30-\nFor media inquiries please contact the EPS Media Relations Unit at\nmediarelations@edmontonpolice.ca\n.\n< Back to Media Releases Listing Page"
  },
  {
    "title": "Police warning of evolving phone scam",
    "url": "https://www.edmontonpolice.ca/News/MediaReleases/BankFraudApril3",
    "date": null,
    "service_name": "Edmonton Police Service",
    "content": "Police warning of evolving phone scam\nFor Immediate Release:\n03-Apr-2026 @ 5:30 PM\nMRU #:\n26R032\nThe Edmonton Police Service (EPS) has arrested a 21-year-old male in relation to a phone scam series that has occurred throughout Edmonton in the last month.\nIn late March 2026, the EPS became aware of a trend involving suspects claiming to be official bank representatives. These individuals are calling Edmontonians and stating that their bank cards have been compromised, and their cards are required to be placed in an envelope for collection. A driver then attends their residence and collects the package. The victims later learn their cards have been used for unauthorized purchases or cash withdrawals.\nOn April 2, 2026, officers arrested and charged\nCheng-Tso (Josh) Huang, 21\n, of Toronto, Ont. with\nfraud\n. He remains in custody, and his next court date is Tuesday, Apr. 7, 2026, in Edmonton.\n“We are working to try to identify additional suspects,” says Det. Tyson Sergent with the EPS’ Investigative Response Team. “If you believe you were victimized by such a scam, we encourage you to contact your financial institution immediately and to report such crimes to the police.”\nPolice are warning people to be vigilant when discussing their personal banking over the phone and consider the following recommendations:\nNever share your PIN or personal information over the phone\nVerify unexpected calls about your banking accounts in person at your financial institution\nMonitor bank and credit card statements monthly for unauthorized transaction\nAnyone who believes they have been victimized or has information about the people involved in these phone scams is encouraged to contact police at 780-423-4567 or #377 from a mobile phone. Anonymous information can also be submitted to Crime Stoppers at 1-800-222-8477 or online at\nwww.p3tips.com/250\n.\n-30-\nFor media inquiries please contact the EPS Media Relations Unit at\nmediarelations@edmontonpolice.ca\n.\n< Back to Media Releases Listing Page"
  },
  {
    "title": "Public Information and Warning: Sexual Offender released",
    "url": "https://www.edmontonpolice.ca/News/MediaReleases/BAUApril2",
    "date": null,
    "service_name": "Edmonton Police Service",
    "content": "Public Information and Warning: Sexual Offender released\nFor Immediate Release:\n02-Apr-2026 @ 3:00 PM\nMRU #:\nH260002\nIn the interest of public safety, the Edmonton Police Service is issuing the following warning: Alfred David White, 39, is a convicted child sex offender, and the Edmonton Police Service has reasonable grounds to believe he will commit another sexual offence against a child while in the community.\nIn 2018,\nWhite\ncommitted sexual offences against children in Calgary. He was subsequently arrested and convicted in 2020, receiving a two‑year custodial sentence. While on judicial interim release,\nWhite\ncommitted additional offences in Calgary involving the possession of child pornography between 2019 and 2020. He was convicted of these offences in 2021 and received an additional 15‑month consecutive sentence. Following his statutory release in 2022,\nWhite\nreoffended in 2023 by accessing and uploading child pornography. He was arrested and in early January 2024 was convicted of possessing child pornography and breaching a prohibition order and was sentenced to 27 months incarceration.\nUpon\nWhite’s\nrelease, he will\nreside in Edmonton.\nGiven\nWhite’s\ncriminal history and his high risk of reoffending, the Edmonton Police Service has sought and obtained court-imposed conditions. Upon his release,\nWhite\nwill be subject to numerous conditions including the following\n:\nYou will not attend within 100 meters of a public park, public swimming area, daycare, school ground, playground, recreational centers, community centers, youth shelters, public libraries, or any other area where persons under the age of 16 are present or can reasonably expected to be present unless you have received written approval from your Supervisor or designate.\nYou shall have no contact or attempted contact (including written, or contact over the Internet, or any form of electronic communication) with any child under the age of 16 years. You shall not enter a personal or intimate relationship with any person until his/her identity has been disclosed to your Supervisor and he/she has been informed by your Supervisor of your prohibitions regarding contact with children under the age of 16.\nYou shall have no contact, direct or indirect, with the victims of your index offence.\nYou shall not associate with anyone known to have a criminal record for sexual offences except for participants in a program or individuals approved by your Supervisor.\nYou must live at a residence approved by the Alberta Court of Justice or your Supervisor, and you must not change that address until you have received written approval from your Supervisor.\nWhite’s\ncompliance with these conditions will be monitored and managed by the Behavioural Assessment Unit of the Edmonton Police Service.\nAnyone with any information about\nWhite’s\nbehavior/conduct while in the community\ncan contact the EPS at 780-423-4567.\nThe Edmonton Police Service is issuing this information and warning after careful deliberation of all related issues, including privacy concerns, in the belief that it is clearly in public interest to inform members of the community.\nThe information in this release is that which was verifiable prior to the release time indicated. Continued investigation and review could result in additional information or clarification.\nAlfred David White (39)\nHeight: 6’2” | Weight: 345 lbs\nEyes: Blue | Hair: Brown\nMembers of the public are advised that the intent of this process is to enable citizens to take suitable precautionary measures. Releasing this information is NOT intended to encourage people to engage in any form of vigilante action\n.\nThis information is released under the authority of Section 37(1) of the Access to Information Act (ATIA)\nThe information in this release is that which was verifiable prior to the release time indicated. Continued investigation and review could result in additional information or clarification.\n-30-\nFor media inquiries please contact the EPS Media Relations Unit at\nmediarelations@edmontonpolice.ca\n.\n< Back to Media Releases Listing Page"
  },
  {
    "title": "Three arrested, multiple charges laid in ongoing Kijiji and Facebook marketplace robberies",
    "url": "https://www.edmontonpolice.ca/News/MediaReleases/kijijiFBrobberiesarrestMar",
    "date": null,
    "service_name": "Edmonton Police Service",
    "content": "Three arrested, multiple charges laid in ongoing Kijiji and Facebook marketplace robberies\nFor Immediate Release:\n01-Apr-2026 @ 12:30 PM\nMRU #:\n26R031\nThe Edmonton Police Service (EPS) has charged two males and\none female in a relation to a string of Kijiji and Facebook Marketplace\nrobberies that took place between late February and early March.\nEarlier this year, EPS issued a\nnews release\nregarding an ongoing series of personal robberies involving Kijiji and Facebook Marketplace sales of higher-priced items, such as newer Apple iPhone and computer products. In each case, a suspect posing as a buyer meets up with the seller, evaluates the item(s) for sale and then robs the seller of the item, often using bear spray, uttering threats or presenting a firearm. Sometimes, the robbery involves more than one suspect. Additionally, the suspects have been known to sell fake iPhones to unsuspecting buyers and/or use counterfeit money.\nThanks to ongoing efforts by EPS Patrol and Investigative Response Teams (IRT), three adults were arrested late last month and charged with a combined total of 30 offences in relation to eight separate incidents:\nCody Bear, 18,\nis facing 23 charges, including\nrobbery (x5),\nattempted robbery (x2)\nand\npossession of a weapon (x5).\nDelvoi Sadiki, 19,\nis facing six charges including\nrobbery (x2), assault with a weapon (x2)\nand\ndisguise with intent\n(x2)\nArianna Mejia, 19,\nis charged with one count of\nrobbery.\nSince mid-December, police have received 53 reports of these incidents. While a large portion of the robberies took place in the Hillview and Richfield neighbourhoods, detectives can confirm they are taking place citywide. At this time, the robberies remain ongoing and investigators believe the crimes are being committed by multiple individuals who are not always connected. Police are warning people to be vigilant when arranging online sales meetups and consider the following recommendations:\nDo not meet in a secluded place or invite strangers into your home.\nSuggest meeting during the day at one of the\nEPS Buy and Sell Exchange Zones.\nAsk the buyer/seller for photo ID.\nTake a photo of it for your reference.\nTake screenshots\nof the advertisements, the advertisement ID number, the seller's/buyer’s contact information, and all communications.\nObtain a bill of sale and verify the seller's identity through photo ID.\nInform the seller that you want this before meeting; this will deter those selling illegitimate property from selling the property.\nDo not disclose to the seller how you will be paying if it's not necessary.\nIf the seller is aware that you will be arriving with a large quantity of cash, it is an excellent opportunity for a personal robbery to take place.\n“We are pleased to share that we have made some arrests in relation to these incidents and want Edmontonians to know that we continue to diligently investigate these offences,” says Staff Sergeant Eric Stewart, with the EPS Investigative Response Team. “If you are buying or selling items on online platforms, remember to put your safety first and trust your instincts. If something feels off at any point, it probably is and it’s best to abandon the transaction.”\nFor more information about online buying and selling safety and EPS Buy and Sell Exchange Zones visit the\nEPS website\n.\n-30-\nFor media inquiries please contact the EPS Media Relations Unit at\nmediarelations@edmontonpolice.ca\n.\n< Back to Media Releases Listing Page"
  },
  {
    "title": "Male charged after knife attack on police",
    "url": "https://www.edmontonpolice.ca/News/MediaReleases/AttemptedMurderMarch30",
    "date": null,
    "service_name": "Edmonton Police Service",
    "content": "Male charged after knife attack on police\nFor Immediate Release:\n30-Mar-2026 @ 2:05 PM\nMRU #:\n26R028\nThe Edmonton Police Service (EPS) has charged a 33-year-old male with attempted murder and other criminal offences following an investigation into two incidents that occurred in central Edmonton at the beginning of the month.\nOn Mar. 1, 2026, at around 10:30 p.m. a Transit Peace Officer (TPO) and two EPS officers were conducting proactive patrol of Corona LRT Station when they observed a male openly consuming alcohol. When the male was approached, he pulled out a concealed knife and attempted to stab the responding officers. Thankfully, nobody was injured and the male was arrested.\nShortly after the arrest, EPS officers determined that the 33-year-old male was involved in a robbery of a central Edmonton liquor store in the area of 113 Street and Jasper Avenue approximately 30 minutes before the incident at Corona Station.\nMorgan Banman, 33,\nis facing charges for\nattempted murder\n(x2),\nassaulting a peace officer with a weapon\n(x3),\npossession of a weapon for a dangerous purpose\n, and\nrobbery\n.\n“While we are grateful that no officers or members of the public were injured, this incident serves as a stark reminder of the dangers all levels of law enforcement face on a daily basis,” says Inspector Jon Morrison with the EPS’ Investigative Response Team. “This is also an example of how crime and disorder continue to impact all corners of our city; from the business that was robbed, to the LRT patrons who may have felt unsafe during their commutes, to the officers on proactive duty who were attacked with a weapon. This is why we must continue to have a proactive presence in public spaces.”\nAnyone with any information about this or any other crime is asked to contact the EPS at 780-423-4567\nor #377 from a mobile phone. Anonymous information can also be submitted to Crime Stoppers at 1-800-222-8477 or online at\nwww.p3tips.com/250\n.\n-30-\nFor media inquiries please contact the EPS Media Relations Unit at\nmediarelations@edmontonpolice.ca\n.\n< Back to Media Releases Listing Page"
  },
  {
    "title": "Celebrating 50 years of community heroes",
    "url": "https://www.edmontonpolice.ca/News/MediaReleases/Celebrating50yearsofcommunityheroes",
    "date": null,
    "service_name": "Edmonton Police Service",
    "content": "Celebrating 50 years of community heroes\nNominate the next Kiwanis Top Cop\nFor Immediate Release:\n30-Mar-2026 @ 8:00 AM\nMRU #:\n26R027\nKiwanis is inviting the public to help recognize police officers dedicated to improving the lives of others beyond their regular duties.\n“For 50 years, the Top Cop Award has recognized the volunteer service of our city’s police officers and their commitment to give back to the community,” says Beverly Levis, President of the Kiwanis Edmonton Oil Capital Club.\n“We invite Edmontonians to help us celebrate this remarkable milestone by nominating an officer who exemplifies the values of leadership, compassion, and community-building that Kiwanis and EPS stand for.”\nEstablished through a partnership between the local Kiwanis Edmonton Oil Capital Club and the Edmonton Police Service in 1975, the award was created to recognize “meritorious community service” rather than contributions to law enforcement, which was unique for police awards at the time.\nThe first Top Cop Award was presented in 1976 to Staff Sergeant Joe Dumonceaux, who was recognized for his involvement in community league activities, and his leadership as a coach and official working to reduce violence in minor hockey.\nFive decades later, the spirit behind that first award lives on through officers who give back to their communities in remarkable ways.\nLast year’s Top Cop, Constable Thomas Cleal, was recognized for his leadership supporting Special Olympics Alberta through the Law Enforcement Torch Run, the Polar Plunge, and Cops, Pops and Pizza.  Through his tireless volunteer efforts, Cleal has helped raise awareness and vital funds so athletes with intellectual disabilities can train, compete and thrive.\nTop Cops exemplify what it means to lead with heart, making valuable contributions whether coaching children’s sports, mentoring youth, supporting seniors, raising funds for charities or community leagues, or helping the less fortunate.\n“Police officers are often humble about their volunteer work, but their commitment to giving back reflects how deeply they care about the community beyond their duties,” says Superintendent Bart Lawczynski of the Edmonton Police Service.\n“That’s what makes the Kiwanis Top Cop Award so meaningful, it helps to shine a spotlight on officers who serve with heart well beyond the uniform, often inspiring others to follow in their footsteps.”\nThe Kiwanis Club will announce the 50th Top Cop at a formal ceremony and present a $1,000 donation to a charity or non-profit of the winner’s choice, helping to extend the impact of their volunteer efforts.\nMembers of the public and community organizations are encouraged to submit nominations for the Top Cop Award before April 30, 2026.\nTo nominate an officer or learn more about the award, please visit\nwww.edmontonpolice.ca/topcop\n.\n-30-\nFor media inquiries, please contact Chad Orydzuk with the EPS Public Affairs Unit at\nchad.orydzuk@edmontonpolice.ca\n.\n< Back to Media Releases Listing Page"
  },
  {
    "title": "Police lay charges in relation to missing person investigation",
    "url": "https://www.edmontonpolice.ca/News/MediaReleases/homicidesuttonMar26",
    "date": null,
    "service_name": "Edmonton Police Service",
    "content": "Police lay charges in relation to missing person investigation\nFor Immediate Release:\n27-Mar-2026 @ 10:15 AM\nMRU #:\nMP25R046-1\nThe Edmonton Police Service (EPS) has charged a\n47-year-old Prince Edward Island man in relation to the death of a missing\nwoman.\nMarika\naka\n“Mika” Sutton, 29,\nwho\nwas last seen in early August 2025 in the Richfield neighbourhood in Mill Woods, southeast Edmonton. Marika was reported missing to the EPS on Sept. 25, 2025, by out of province family, and police immediately began investigating. A media release seeking the public’s assistance locating Marika was issued on\nOct. 8, 2025.\nBy the end of October, investigations led police to believe that Marika was deceased, and her disappearance was criminal in nature. As a result, EPS Homicide Section assumed the investigation on Oct. 22, 2025, and on March 17, 2026, travelled to Charlottetown, P.E.I where they arrested and charged\nJohn Angus Joseph MacArthur, 47,\nwith\nsecond degree murder\nand\nindignity to a body.\nMacArthur was transported back to Edmonton on March 20 and has since been remanded.\nMacArthur and Sutton were known to one another and in an intimate partner relationship. While not formally reported to police, a history of domestic violence was uncovered during the investigation. As such, Marika’s death is considered an intimate partner homicide.\nInvestigators continue to search for Marika’s remains and believe that McArthur may have disposed of her body somewhere along Highway 2 between Wetaskiwin and Lacombe,\nAlberta\nbetween Aug. 22-29, 2025. MacArthur was driving a 2014 black Jeep Patriot at the time with Alberta license plate: CFB 2578.  A photo of his vehicle is included below.\nMacArthur’s 2014 Jeep Patriot\n2014 Jeep Patriot\nAB license plate: CFB 2578\n“To protect the integrity of the investigation and secure the arrest of the accused, we deliberately chose to deviate from our normal process of immediately notifying the public of Marika’s death,” says Det. Braydon Lawrence with the EPS Homicide Section. “That being said, we are hopeful that someone travelling on Highway 2 between Wetaskiwin and Lacombe between Aug. 22 and Aug. 29 may recall seeing MacArthur’s Jeep in a strange or unusual location, and if so, we encourage them to contact us immediately.”\n“Likewise, we are appealing to any landowners, hunters and outdoor enthusiasts who may frequent this area to be on the lookout for Marika’s remains.”\nInvestigators would like to thank the EPS Edmonton Drug and Gang Enforcement (EDGE) Team, the Calgary Police Services and the Charlottetown Police Service for their assistance with this investigation.\nAnyone with information about\nMarika Sutton’s\ndisappearance or death is asked to contact the EPS at 780-423-4567\nor #377 from a mobile phone. Anonymous information can also be submitted to Crime Stoppers at 1-800-222-8477 or online at\nwww.p3tips.com/250\n.\n-30-\nFor media inquiries please contact the EPS Media Relations Unit at\nmediarelations@edmontonpolice.ca\n.\n< Back to Media Releases Listing Page"
  },
  {
    "title": "Police seek dashcam footage in collision investigation",
    "url": "https://www.edmontonpolice.ca/News/MediaReleases/collisionMar11",
    "date": null,
    "service_name": "Edmonton Police Service",
    "content": "Police seek dashcam footage in collision investigation\nFor Immediate Release:\n11-Mar-2026 @ 5:05 PM\nMRU #:\nTR26004\nThe Edmonton Police Service\n(EPS) is seeking dashcam footage in relation to yesterday’s pedestrian\ncollision.\nAt approximately 12 p.m., on Tuesday, Mar. 10, 2026, two 16-year-old females were crossing 122 Avenue at 96 Street when they were struck by an SUV operated by a 62-year-old male, who remained on scene.\nThe pedestrians were treated and transported to the hospital with serious, non-life-threatening injuries. At this time, neither speed nor alcohol are considered factors in the collision.\nEPS Major Collision Investigations Section (MCIS) is investigating the collision and is asking a\nnyone who witnessed or has dashcam footage of this event to contact EPS at 780-423-4567 or #377 from a mobile phone.\n-30-\nFor media inquiries please contact the EPS Media Relations Unit at\nmediarelations@edmontonpolice.ca\n.\n< Back to Media Releases Listing Page"
  },
  {
    "title": "Police warn of steady number of sextortion cases targeting youth in Edmonton",
    "url": "https://www.edmontonpolice.ca/News/MediaReleases/YouthSextortionPublicSafetyMarch112026",
    "date": null,
    "service_name": "Edmonton Police Service",
    "content": "Police warn of steady number of sextortion cases targeting youth in Edmonton\nFor Immediate Release:\n11-Mar-2026 @ 10:01 AM\nMRU #:\nSA26R003\nThe Edmonton Police Service (EPS) is warning parents, caregivers, and youth about an ongoing and persistent number of sextortion cases targeting young people in Edmonton.\nOverall, between 2018 and 2025, the EPS received 983 sextortion-related reports involving youth victims. In all of 2025, the EPS receive 168 occurrences.\n“Kids are online more than ever, and predators know it,” says Acting Inspector Paul Looker from the EPS Community and Youth Response Branch. “Sextortion has moved from being a rare online scam to something our School Resource Officers encounter regularly.”\nSextortion occurs when an offender coerces a victim into sending sexually explicit images or videos, then threatens to release the content publicly or share it with family and friends unless money, gift cards, or more images are provided. Even after a victim complies, offenders will often escalate their demands.\n“We’re seeing students as young as 13 being targeted. These crimes are emotionally devastating, and they thrive in secrecy. We want youth and parents to know how to spot the warning signs and how to get help immediately,” explains A/Insp. Looker.\nEPS analysis shows:\nMost victims are between 13 and 16 years old, with 15 being the most common age.\n68% of victims are female, 31% are male, and 1% are unspecified.\nMale youths as victims are on an upward trend, increasing each year.\nOffenders are predominantly male (84%), with some as young as 16.\nAdults account for 55% of offenders in reported cases, while 35% are youth under 18.\n​\nPolice are encouraging parents and caregivers to talk with their kids early, ideally before the high-risk ages of 13 to 16, about online safety and how to respond if someone asks for sexual images.\nEPS works routinely with the Alberta Law Enforcement Response Team (ALERT) on files involving sextortion. In an effort to educate and prevent future cases of online exploitation, ALERT’s Internet Child Exploitation (ICE) unit established a community engagement team in 2024.\nThis team travels across the province, providing education to help children, teens and parents learn about real-life examples of the dangers found online.\n“Conversations around internet safety don’t have to be confusing. We tell parents that the same lessons you share with your children about how to be safe on the playground, or at the mall, apply online,” said Const. Stephanie Bosch from ALERT ICE. “We teach our kids to not give out private information to strangers or to get into vehicles with people they don’t know – these lessons translate to online safety when we talk about locking down profiles, turning off location services, or the dangers of moving from an open platform to a secured app.”\nWarning signs to watch for:\nThese could be red flags, not proof that something is wrong.\nSuddenly becomes more secretive about their phone or screen time\nWithdraws from friends or activities\nHas unexplained anxiety or mood swings\nA sudden drop in school performance\nLogs out quickly, hides apps, or seems guarded about online interactions.\nHeightened anxiety, or unexplained urgency to meet someone.\n​\n“The sooner a student can talk to a trusted adult or their School Resource Officer, the sooner we can intervene and prevent more harm from happening,” says A/Insp. Looker.\nRegularly talk to your child about their online activities — not just once.\nBuild trust so your child feels safe coming to you if something goes wrong.\nTake interest and learn about the apps, games and platforms your child uses.\nAsk questions about their online friends and what’s happening in their digital world.\n​\n“There is no such thing as a bad app, just the bad behavior that can occur on any app. By teaching youth about the behaviours to be on the lookout for, we help instill confidence, which will help them recognize when harm may happen,” Const. Bosch added.\nEPS School Resource Officers (SRO) and community partners will be increasing education efforts in schools and online to help prevent sextortion.\n“Every student should feel a sense of belonging and safety within their school community,” said Ron Thompson, Superintendent of Edmonton Public Schools. “Together with our community partners and the Edmonton Police Service, we want students and families to know that support is available and no student has to face these challenges alone.”\nAnyone who believes they or someone they know is being victimized should contact police at\n780-423-4567\nor #377 from a mobile phone. Anonymous information can also be submitted to Crime Stoppers at 1-800-222-8477 or online\nat\nwww.p3tips.com/250\n.\n-30-\nFor media inquiries please contact the EPS Media Relations Unit at\nmediarelations@edmontonpolice.ca\n.\n< Back to Media Releases Listing Page"
  },
  {
    "title": "Two charged in 2024 homicide",
    "url": "https://www.edmontonpolice.ca/News/MediaReleases/2024homicideMar9",
    "date": null,
    "service_name": "Edmonton Police Service",
    "content": "Two charged in 2024 homicide\nFor Immediate Release:\n09-Mar-2026 @ 2:42 PM\nMRU #:\nH24R024-2\nThe Edmonton Police Service Homicide Section has\narrested two males in connection with a May 2024 homicide.\nTristan Dylan Green, 29\n, and\nDorian Gladue Thomas, 25\n, were arrested on Feb. 4, 2026, and March 8, 2026, respectively, in connection to the homicide of Jordan Belhumeur. They are each facing a charge of\nsecond-degree murder\n.\nBackground\nOn Monday, May 27, 2024, at approximately 3:30 a.m., police responded to a weapons complaint in the area of 127 Avenue and 118 Street. Upon arrival, they located an adult male suffering from a serious injury. EMS treated and transported the male to hospital, where he later died.\nOn Wednesday, May 29, 2024, the Edmonton Medical Examiner conducted an autopsy and determined that Jordan Belhumeur, 37, died of a gunshot wound. The manner of death was confirmed to be homicide.\n-30-\nFor media inquiries please contact the EPS Media Relations Unit at\nmediarelations@edmontonpolice.ca\n.\n< Back to Media Releases Listing Page"
  },
  {
    "title": "Newest EPS police officers graduate",
    "url": "https://www.edmontonpolice.ca/News/MediaReleases/RTC164Graduation",
    "date": null,
    "service_name": "Edmonton Police Service",
    "content": "Newest EPS police officers graduate\nRecruit Training Class 164 ready for duty\nFor Immediate Release:\n06-Mar-2026 @ 10:00 AM\nMRU #:\n26R022\nThe Edmonton Police Service (EPS) is welcoming the newest group of police officers this week as 45 recruits from Recruit Training Class (RTC) 164 graduate at City Hall at on Friday, March 6, 2026.\nThe graduating class brings a wide range of professional and personal experiences to the service. Members of RTC 164 come from backgrounds including law enforcement, corrections, the military, firefighting and laboratory sciences. While many recruits are from Alberta or come from other parts of Canada, others come from countries such as India, Jamaica, Republic of Congo, Scotland, Ukraine, and the United Kingdom.\n​\n“Our newest officers represent the many cultures, backgrounds and voices that make our city vibrant,” says Acting Staff Sergeant Selena Gavins with the EPS Recruit Training Section. “Their diversity isn’t just a point of pride, it’s essential to building trust and delivering policing that truly reflects the community we serve.”\nEPS, named one of Alberta’s Top Employers for the sixth time, continues to emphasize hands-on, real-world training that extends beyond classroom learning. This approach ensures new officers are better prepared to understand and assist Edmonton’s diverse and vulnerable populations.\nRTC 164 demonstrated strong community spirit throughout their training, volunteering over 950 hours of their own time. Their efforts supported several EPS and Edmonton Police Foundation (EPF) events including Find Santa, Christmas Bureau, and the Edmonton Police Foundation Half Marathon.\nIn 2025, EPS expanded its recruitment outreach efforts through over 60 events and numerous presentations to community-groups, schools, and post-secondary institutions. Working closely with the EPS Equity, Inclusion & Human Rights Branch, recruitment teams increased their focus on Indigenous engagement to strengthen relationships and raise awareness of career opportunities within policing.\nEPS continues to modernize its recruitment process through technology, public feedback, and personalized strategies, which include initiatives such as Women in Policing, the Athlete to Officer Program, and Experienced Officer program.\n​\nWith their training complete, the new constables now enter their field development stage with the Service’s Community Policing Bureau. Afterwards, they will return for some additional assessment and training to maximize their potential.\nFor more information about a career with EPS, please visit\njoinEPS.ca\n-30-\nFor media inquiries please contact the EPS Media Relations Unit at\nmediarelations@edmontonpolice.ca\n.\n< Back to Media Releases Listing Page"
  },
  {
    "title": "Police and community partners raise awareness to help Edmontonians outsmart fraud this March",
    "url": "https://www.edmontonpolice.ca/News/MediaReleases/FraudPreventionMonth_2026",
    "date": null,
    "service_name": "Edmonton Police Service",
    "content": "Police and community partners raise awareness to help Edmontonians outsmart fraud this March\nFor Immediate Release:\n04-Mar-2026 @ 8:00 AM\nMRU #:\n26R020\nMarch 2026 marks the 22nd anniversary of Fraud Prevention Month in Canada. According to an online poll from Leger a quarter of Canadians say they have been the victim of fraud or extortion.\nThe Edmonton Police Service (EPS) and community partners are raising awareness to help protect Edmontonians from fraud.\nEPS will join provincial community partners to shine a spotlight on fraud prevention and help residents protect themselves from financial crime. Throughout Fraud Prevention Month, partners will be sharing practical tools, raising awareness, and as a result reducing victimization across the city.\nOver the course of the month, partners will be using social media, outreach campaigns, and educational materials to highlight the most frequent types of fraud, which include frauds involving the use of artificial intelligence (AI), investment fraud, online scams, phone/mass marketing scams, and relationship scams.\nThe need for awareness is significant. In 2025, more than 4,000 frauds were reported in Edmonton, with losses exceeding $58 million. Investment and cryptocurrency scams accounted for the largest financial impact with approximately $25 million lost, followed by compromised credit or debit accounts, identity theft and phishing scams. Investigators believe the real numbers are even higher, as many victims never report what happened.\n“Fraudsters are getting more creative, and many are now using AI to make their scams more legitimate and convincing,” says Detective Scott Abbott with the EPS Financial Crimes Section. “We want people to know that even the most tech-savvy individuals can be targeted. If something doesn’t quite sound right, or if a message seems urgent or unusual, it’s important to pause, verify, and reach out to someone you trust. Taking a moment to double check can be the difference between staying safe and becoming a victim.”\nBecause fraud crosses jurisdictions and takes countless forms, strong partnerships are essential. By working together, EPS, and its community partners are helping ensure Edmontonians have the knowledge and confidence to protect themselves in an increasingly complex digital world.\nPartners participating in Fraud Prevention Month include RCMP, Alberta Blue Cross, Alberta Securities Commission, Better Business Bureau, Association of Certified Fraud Examiners, Electronic Recycling Association, Real Estate Council of Alberta, Service Alberta and Red Tape Reduction, Alberta Community Crime Prevention Association, Crime Stoppers, Servus Credit Union, and Edmonton Neighbourhood Watch.\nQuotes from our partnering agencies\n“Fighting fraud is not a one agency mission. It takes all of us. We need to share intelligence across partners, encourage the public to report every instance of fraud, and work together to amplify our resources so Canadians get clear, consistent education on this issue year-round.”\n— Insp. John Lamming, Officer in Charge of Financial Integrity and Cybercrime, RCMP Federal Policing Northwest Region\n“Fraud can take a serious financial and emotional toll on individuals and families, and scammers are constantly finding new ways to exploit emerging technology. Fraud Prevention Month is a reminder for Albertans to stay alert, ask questions, and protect themselves. Alberta’s government will continue to work with law enforcement and community partners to raise awareness, support victims, and make sure consumers have clear, trusted information to make confident decisions.”\n— Dale Nally, Minister of Service Alberta and Red Tape Reduction\nAt the Alberta Community Crime Prevention Association (ACCPA) we are pleased to partner with our police and law enforcement agencies, community, agencies, and consumer groups to chair Alberta Fraud Prevention Month. March is a month of crime prevention initiatives aimed at educating and creating awareness in how to recognize, report and stop Fraud of any nature with our partners and communities.”\n— Jean Bota, ACCPA Executive Director\n“A safer community is a connected community. Share what you know, ask questions, and help stop fraud before it starts.”\n— Edmonton Neighbourhood Watch Program Society\n“As Alberta’s largest benefit provider, Alberta Blue Cross has a responsibility to protect the integrity of the plans entrusted to us. Fraud and plan abuse ultimately impact employers, plan members, and the sustainability of benefits for everyone. Fraud Prevention Month is an important opportunity to raise awareness, reinforce vigilance, and underscore our commitment to preventing fraud wherever it occurs.”\n— Brian Geislinger, Senior Vice-President of Corporate Relations and Community Engagement with Alberta Blue Cross.\n“Outdated electronics are one of the most overlooked fraud risks. Proper reuse, secure data wiping, and responsible recycling are essential steps in protecting Canadians from data breaches and identity theft.”\n— Bojan Paduh, Founder & President, Electronic Recycling Association\n“Crime Stoppers plays a role in fraud prevention by giving people a safe, anonymous way to report suspicious activity, helping law enforcement stop fraud schemes before more victims are affected. Whether you live in Edmonton or a rural community, that information can help prevent further harm.”\n– Chris Holtz, President – Crime Stoppers Association of Edmonton and Northern Alberta\n\"The Better Business Bureau Serving Alberta and East Kootenay is honoured to once again take part in Fraud Prevention Month. We know scams and scammers are getting more sophisticated. However, we also know these same scammers can be stopped through scam prevention knowledge and taking action. Together with all of our partners, this month represents a meaningful opportunity to reach consumers and businesses and provide them with invaluable information on how fraud and scams can be prevented this month and every month.\"\n–Mary O’Sullivan-Andersen, President and CEO, The Better Business Bureau\n“Today’s most common investment scams move quickly and leverage technology and social media, making them harder to detect. Albertans should be cautious of anyone promising guaranteed returns or low risk, high reward opportunities as these are major red flags. We are proud to partner with organizations across the province during Fraud Prevention Month to raise awareness of investment fraud and to provide trusted resources, such as those available on\nCheckFirst.ca\n, that can help Albertans make informed decisions.”\n–Hilary McMeekin, Director of Communications and Investor Education with the Alberta Securities Commission\n“As fraud becomes more sophisticated, it’s critical consumers ensure they are working with a licensed professional. RECA licenses and regulates real estate, mortgage, property management and condominium management professionals across Alberta to help protect the public. Before you sign anything, verify your professional’s licence using RECA ProCheck, and visit\nrecaprotects.ca\nfor consumer fraud prevention tips.”\n– Stacey Paquin, Chief Executive Officer of the Real Estate Council of Alberta\nFollow EPS on social media and visit\nEdmontonpolice.ca/fraud\nfor more information on common scams and how to spot them.\n-30-\nFor media inquiries please contact the EPS Media Relations Unit at\nmediarelations@edmontonpolice.ca\n.\n< Back to Media Releases Listing Page"
  },
  {
    "title": "Police warn of residential break and enters",
    "url": "https://www.edmontonpolice.ca/News/MediaReleases/residentialBEsMar3",
    "date": null,
    "service_name": "Edmonton Police Service",
    "content": "Police warn of residential break and enters\nFor Immediate Release:\n03-Mar-2026 @ 8:55 AM\nMRU #:\n26R019\nThe Edmonton Police Service is alerting Southwest\nravine-area residents to a string of residential break and enters.\nSince January 2026, police\nare investigating seven residential break and enters occurring in the earlier evening hours in homes primarily near the Whitemud and Blackmud Creek ravines. The houses appear to be targeted at random; however, the suspects almost exclusively enter when the occupants are not at home.\nThe suspects typically gain access to the homes by smashing the glass in a rear window or rear door. Once inside, they head straight to the primary suite to locate jewelry and high-end clothing, then quickly flee to a newer model vehicle waiting outside. Surveillance video has captured a Silver GMC Terrain believed to be a 2024-2026 model, and a Ford Escape, possibly ST edition, believed to be a 2023-2026 model.\nSuspect vehicle: newer model silver GMC Terrain\nSuspect vehicle: newer model Ford Escape\nTo help protect their property, police advise homeowners:\nLeave lights on inside when leaving the residence.\nDo not post to social media about travel plans.\nHave someone check on your house while you’re away on vacation, bring in mail, put out garbage bins, cut grass or shovel snow, etc.\nInvest in a home security system that includes motion and glass-break sensor and interior cameras.\nInstall motion-activated lights.\nPlace valuable items in a safe or well-hidden location.\nKeep serial numbers and photos of valuables so they can be traced if stolen.\nMore information about home security is available on the EPS\nwebsite\n.\nResidents are asked to report suspicious activity, including suspicious vehicles that are seen idling in your area to police.\nCall 911 if you witness a crime in progress, or for non-emergencies, call 780-423-4567\nor #377 from a mobile phone. Anonymous information can also be submitted to Crime Stoppers at 1-800-222-8477 or online at\nwww.p3tips.com/250\n.\n-30-\nFor media inquiries please contact the EPS Media Relations Unit at\nmediarelations@edmontonpolice.ca\n.\n< Back to Media Releases Listing Page"
  },
  {
    "title": "Missing man located",
    "url": "https://www.edmontonpolice.ca/News/MediaReleases/missingmanFeb27",
    "date": null,
    "service_name": "Edmonton Police Service",
    "content": "Missing man located\nFor Immediate Release:\n02-Mar-2026 @ 7:04 PM\nMRU #:\nMP26R007\nPlease be advised that the 56-year-old man reported missing last week has been located. Sadly, he was found deceased, and his death is considered non-criminal.\n-30-\nFor media inquiries please contact the EPS Media Relations Unit at\nmediarelations@edmontonpolice.ca\n.\n< Back to Media Releases Listing Page"
  },
  {
    "title": "Police investigating hit and run; seek suspect vehicle",
    "url": "https://www.edmontonpolice.ca/News/MediaReleases/HitAndRunFeb26",
    "date": null,
    "service_name": "Edmonton Police Service",
    "content": "Police investigating hit and run; seek suspect vehicle\nFor Immediate Release:\n26-Feb-2026 @ 2:41 PM\nMRU #:\nTR26003\nThe Edmonton Police Service (EPS) is seeking the public's assistance identifying a vehicle involved in a hit-and-run collision earlier this month.\nAt approximately 10:11 p.m., on Thursday, Feb. 5, 2026, police responded to a report of a hit-and-run collision in the McCauley neighbourhood. It was reported to police that a suspect SUV entered 107 Avenue from an alley west of 95 Street.\nT\nhe SUV was seen driving the wrong way on a portion of 107 Avenue before it struck a female in the roadway just west of the intersection at 95 Street. The SUV then fled the scene and was last seen heading south on 95 Street.\nThe 31-year-old female pedestrian was sent to hospital with serious injuries.\nEPS Major Collision Investigations Section (MCIS) is investigating the collision and officers are asking the public to contact them if they recognize or have footage of the suspect SUV, as pictured below.\nGrey or light blue suspect SUV\nBack of suspect SUV\nFront of suspect SUV\nAnyone who witnessed or has dashcam footage of this collision is asked to contact EPS at 780-423-4567 or #377 from a mobile phone.\n-30-\nFor media inquiries please contact the EPS Media Relations Unit at\nmediarelations@edmontonpolice.ca\n.\n< Back to Media Releases Listing Page"
  },
  {
    "title": "Police arrest three males following “Jaws of Life” break-and-enters",
    "url": "https://www.edmontonpolice.ca/News/MediaReleases/JawsofLifeFeb26",
    "date": null,
    "service_name": "Edmonton Police Service",
    "content": "Police arrest three males following “Jaws of Life” break-and-enters\nFor Immediate Release:\n26-Feb-2026 @ 8:58 AM\nMRU #:\n26R013\nEdmonton Police Service (EPS) officers have charged three men following a series of break-ins that occurred across Edmonton and surrounding areas between December 2025 and January 2026.\nBetween November and December 2025, the EPS became aware of reports of break-and-enters at firehalls in Water Valley and Calahoo. In both occurrences, it was reported that rescue tools including industrial cutters, a ram and spreaders commonly referred to as the “Jaws of Life” were taken from the properties, with the total amount of these tools valued at approximately $110,000.\nIn late December, Sturgeon County issued a\nrelease\nabout the break-and-enter in Calahoo.\nFrom Dec. 1, 2025, to Jan. 8, 2026, the EPS investigated approximately 18 break-and-enters in Edmonton, of which 14 involved the stolen “Jaws of Life” tools.  In total, 10 break-and-enters were reported in Southwest Edmonton, five were reported in Southeast Edmonton, two were reported in Northeast Edmonton and one was reported in Sherwood Park. These occurred at various types of retail businesses, and the owners are not known to one another\n.\nIn total, police estimate property damages and retail losses range between $750,000 and $1 M. Items that were stolen from these businesses include high-end bags and jackets, cannabis and vape products and cash from ATMs and safes.\nRecovered from Calahoo fire hall (L-R):\nsaw, “combi-tool”, spreader, hoses, b-post simulator, cutter and power pump\nIn late January 2026, police arrested\nLogan Murrell, 30,\nand\nTristin Kaiser, 42.\nIn early February 2026, police arrested\nAbram Dyck, 47.\nAll three males are facing over 200 charges combined, including\nbreak and enter to commit theft\n(x35),\ndisguise with intent\n(x35) and\npossession of stolen property over $5,000\n(x42).\n“The EPS was able to lead a successful cross-agency partnership to combat a break-and-enter series that impacted multiple communities in Alberta,” says Acting S/Sgt. Meagan McIntyre with the EPS’ Southwest Branch. “Through our collaboration with local RCMP detachments, the EPS arrested individuals who caused nearly $1 million in damages to retailers in Edmonton.”\n“This investigation highlights the harm that one small group of offenders can cause to communities,” says S/Sgt. Darcy McGunigal, the Commander of the Morinville RCMP, “Strong partnerships between policing agencies are essential to combating prolific offenders. We thank the officers of the Edmonton Police Service for their continued dedication.”\nCourt dates for\nMurrell, Dyck\nand\nKaiser\nhave not been set at this time.\n-30-\nFor media inquiries please contact the EPS Media Relations Unit at\nmediarelations@edmontonpolice.ca\n.\n< Back to Media Releases Listing Page"
  },
  {
    "title": "Investigators seek public assistance identifying suspects in interprovincial fraud network",
    "url": "https://www.edmontonpolice.ca/News/MediaReleases/ATIfraudsuspectsFeb25",
    "date": null,
    "service_name": "Edmonton Police Service",
    "content": "Investigators seek public assistance identifying suspects in interprovincial fraud network\nFor Immediate Release:\n25-Feb-2026 @ 9:30 AM\nMRU #:\n25R023-2\nThe Edmonton Police Service (EPS) is seeking the public’s assistance identifying\nseveral suspects believed to be involved in an ongoing multi-province debit and\ncredit card fraud network.\nIn January 2025, the EPS received a report that an 85-year-old man was scammed after receiving a call from someone claiming to be a bank employee who stated that his credit cards were being used outside of Edmonton. They instructed him to cut up all his credit and debit cards and give them to an alleged “bank courier”.\nShortly thereafter, two unknown male suspects were captured on surveillance camera using the senior’s credit cards. The fraud amounted to approximately $30,000.\nIn March 2025, the EPS issued a news release containing images of the two suspects, who were subsequently identified as\nAude Gnahore, 22\nand\nMassamba Sow, 38,\nand charged with\nfraud over $5,000\n.\nSince that time, the EPS has received at least 36 reports of the same scam, typically targeting seniors, and in working with the Calgary Police Service and the RCMP, investigators have determined that the same group of suspects is involved in similar scams in Calgary and elsewhere in Canada, including B.C., Manitoba, Ontario and Quebec.\nAt least 24 unknown suspects have been observed in connection to the fraud, and police are releasing surveillance photos in hopes of identifying some of them.\nPictured above: surveillance images of suspects associated with the scam\n“Unfortunately, these types of scams are common, and seniors can be particularly vulnerable,” says Cst. Clayton Tipton with EPS Beats. “We always encourage families to talk to their senior relatives about scams, and remind them that the bank will never call you to ask for your PIN or tell you to cut up your bank card and send it back to them. If you get a call from someone who says they are with your bank, it’s always ok to end the call and then contact the bank yourself to verify the request.”\nFor more information on how to spot a scam, visit the\nEPS website\n.\nAnyone with information about the suspects’ identities is asked to call EPS at 780-423-4567\nor #377 from a mobile phone. Anonymous information can also be submitted to Crime Stoppers at 1-800-222-8477 or online at\nwww.p3tips.com/250\n.\n-30-\nFor media inquiries please contact the EPS Media Relations Unit at\nmediarelations@edmontonpolice.ca\n.\n< Back to Media Releases Listing Page"
  }
]